register_file.v
//register file with 16 D-flip flops (16 bit each)
module st_bit (
    input clk,
    input write,
    input read,
    input reset,
    input [3:0] address,  //address is the 4 bit location of the flip flop numbered from 0-15
    input [15:0] data,  //data to be stored in the given address of the flip flop 
    input [3:0] read1,  //read1 is the 4 bit location of the flip flop from which data is to be read
    input [3:0] read2,  //read2 is the 4 bit location of the flip flop from which data is to be read
    output reg [15:0] value1,  //value1 is the data stored in the flip flop location given by read1
    output reg [15:0] value2  //value2 is the data stored in the flip flop location given by read2
);

  reg [15:0] w[15:0];  //16x 16bit registers used for data read and write

  always @(negedge clk) begin  //write and reset block
    for (integer i = 0; i < 16; i++) begin

      if (reset == 1'b0) begin
        if (write > 1'b0 && address == i) begin
          w[i] <= data;
        end
      end else begin
        w[i] <= {16{1'b0}};
      end


    end
  end

  always @(*) begin  //read block
    if (read > 1'b0) begin
      value1 <= w[read1];
      value2 <= w[read2];
    end
  end

endmodule

testbench.v
module testbench;
  reg clk, reset, write, read;
  reg [15:0] d, data;
  reg [3:0] address, read1, read2;
  wire [15:0] value1, value2;

  st_bit DUT (
      .clk(clk),
      .address(address),
      .reset(reset),
      .data(data),
      .read1(read1),
      .read2(read2),
      .value1(value1),
      .value2(value2),
      .write(write),
      .read(read)
  );

  always #1 clk = ~clk;

  initial begin
    $monitor(
        $time,
        "clk=%b,reset=%b,write=%b,address=%b,data=%b,read=%b,read1=%b,read2=%b,value1=%b,value2=%b,reset=%b",
        clk, reset, write, address, data, read, read1, read2, value1, value2, reset);

    //inputs to the module

    clk <= 0;
    write <= 1'b0;
    address <= 4'b0;
    read <= 1'b1;
    read1 <= 4'b0;
    read2 <= 4'b0;
    data <= 16'b0;
    reset <= 1'b0;

    #5 write <= 1'b1;
    address <= 4'd0;
    data <= 16'd10;
    read <= 1'b1;
    read1 <= 4'b0;
    read2 <= 4'b0;
    reset <= 1'b0;

    #10 write <= 1'b1;
    address <= 4'd3;
    data <= 16'd10;
    read <= 1'b1;
    read1 <= 4'b0;
    read2 <= 4'd3;
    reset <= 1'b0;

    #10 write <= 1'b1;
    address <= 4'd3;
    data <= 16'd7;
    read <= 1'b1;
    read1 <= 4'b0;
    read2 <= 4'd3;
    reset <= 1'b0;

    #10 write <= 1'b0;
    address <= 4'd3;
    data <= 16'd7;
    read <= 1'b1;
    read1 <= 4'd3;
    read2 <= 4'd3;
    reset <= 1'b0;


    #100 $finish;

  end

  initial begin
    $dumpfile("16_bit.vcd");
    $dumpvars;
  end
endmodule

16_bit.vcd
$date
	Thu Jul 21 12:11:53 2022
$end
$version
	Icarus Verilog
$end
$timescale
	1s
$end
$scope module testbench $end
$var wire 16 ! value2 [15:0] $end
$var wire 16 " value1 [15:0] $end
$var reg 4 # address [3:0] $end
$var reg 1 $ clk $end
$var reg 16 % data [15:0] $end
$var reg 1 & read $end
$var reg 4 ' read1 [3:0] $end
$var reg 4 ( read2 [3:0] $end
$var reg 1 ) reset $end
$var reg 1 * write $end
$scope module DUT $end
$var wire 4 + address [3:0] $end
$var wire 1 $ clk $end
$var wire 16 , data [15:0] $end
$var wire 1 & read $end
$var wire 4 - read1 [3:0] $end
$var wire 4 . read2 [3:0] $end
$var wire 1 ) reset $end
$var wire 1 * write $end
$var reg 16 / value1 [15:0] $end
$var reg 16 0 value2 [15:0] $end
$scope begin $ivl_for_loop0 $end
$var integer 32 1 i [31:0] $end
$upscope $end
$upscope $end
$upscope $end
$enddefinitions $end
#0
$dumpvars
b10000 1
bx 0
bx /
b0 .
b0 -
b0 ,
b0 +
0*
0)
b0 (
b0 '
1&
b0 %
0$
b0 #
bx "
bx !
$end
#1
1$
#2
b10000 1
0$
#3
1$
#4
b10000 1
0$
#5
b1010 %
b1010 ,
1*
1$
#6
b1010 !
b1010 0
b1010 "
b1010 /
b10000 1
0$
#7
1$
#8
b10000 1
0$
#9
1$
#10
b10000 1
0$
#11
1$
#12
b10000 1
0$
#13
1$
#14
b10000 1
0$
#15
bx !
bx 0
b11 (
b11 .
b11 #
b11 +
1$
#16
b1010 !
b1010 0
b10000 1
0$
#17
1$
#18
b10000 1
0$
#19
1$
#20
b10000 1
0$
#21
1$
#22
b10000 1
0$
#23
1$
#24
b10000 1
0$
#25
b111 %
b111 ,
1$
#26
b111 !
b111 0
b10000 1
0$
#27
1$
#28
b10000 1
0$
#29
1$
#30
b10000 1
0$
#31
1$
#32
b10000 1
0$
#33
1$
#34
b10000 1
0$
#35
b111 "
b111 /
b11 '
b11 -
0*
1$
#36
b10000 1
0$
#37
1$
#38
b10000 1
0$
#39
1$
#40
b10000 1
0$
#41
1$
#42
b10000 1
0$
#43
1$
#44
b10000 1
0$
#45
1$
#46
b10000 1
0$
#47
1$
#48
b10000 1
0$
#49
1$
#50
b10000 1
0$
#51
1$
#52
b10000 1
0$
#53
1$
#54
b10000 1
0$
#55
1$
#56
b10000 1
0$
#57
1$
#58
b10000 1
0$
#59
1$
#60
b10000 1
0$
#61
1$
#62
b10000 1
0$
#63
1$
#64
b10000 1
0$
#65
1$
#66
b10000 1
0$
#67
1$
#68
b10000 1
0$
#69
1$
#70
b10000 1
0$
#71
1$
#72
b10000 1
0$
#73
1$
#74
b10000 1
0$
#75
1$
#76
b10000 1
0$
#77
1$
#78
b10000 1
0$
#79
1$
#80
b10000 1
0$
#81
1$
#82
b10000 1
0$
#83
1$
#84
b10000 1
0$
#85
1$
#86
b10000 1
0$
#87
1$
#88
b10000 1
0$
#89
1$
#90
b10000 1
0$
#91
1$
#92
b10000 1
0$
#93
1$
#94
b10000 1
0$
#95
1$
#96
b10000 1
0$
#97
1$
#98
b10000 1
0$
#99
1$
#100
b10000 1
0$
#101
1$
#102
b10000 1
0$
#103
1$
#104
b10000 1
0$
#105
1$
#106
b10000 1
0$
#107
1$
#108
b10000 1
0$
#109
1$
#110
b10000 1
0$
#111
1$
#112
b10000 1
0$
#113
1$
#114
b10000 1
0$
#115
1$
#116
b10000 1
0$
#117
1$
#118
b10000 1
0$
#119
1$
#120
b10000 1
0$
#121
1$
#122
b10000 1
0$
#123
1$
#124
b10000 1
0$
#125
1$
#126
b10000 1
0$
#127
1$
#128
b10000 1
0$
#129
1$
#130
b10000 1
0$
#131
1$
#132
b10000 1
0$
#133
1$
#134
b10000 1
0$
